oiseau_authentication_sample_fastapi/app.py
oiseau_authentication_sample_fastapi/README.md
oiseau_authentication_sample_fastapi-0.1.1.dist-info/METADATA
oiseau_authentication_sample_fastapi-0.1.1.dist-info/WHEEL
oiseau_authentication_sample_fastapi-0.1.1.dist-info/RECORD
